{
    "day": "day-8",
    "segmentName": "segment-1",
    "exercises": {
        "on-change": {
            "completed": true
        },
        "proxy-iterable": {
            "completed": false
        },
        "known-prop": {
            "completed": true
        },
        "negative-index": {
            "completed": true
        },
        "set-default-property": {
            "completed": true
        },
        "private-props": {
            "completed": true
        },
        "xprod": {
            "completed": true
        },
        "without": {
            "completed": true
        },
        "values-in": {
            "completed": true
        },
        "values": {
            "completed": true
        }
    }
}