{
    "day": "day-7",
    "segmentName": "segment-2",
    "exercises": {
        "built-in-iterables": {
            "completed": false
        },
        "ackermann": {
            "completed": true
        },
        "aperture": {
            "completed": true
        },
        "animal-sort": {
            "completed": true
        },
        "args-string": {
            "completed": false
        },
        "arithmetic-expression-evaluator": {
            "completed": false
        },
        "array-addition": {
            "completed": false
        },
        "array-cube-root-to-json": {
            "completed": true
        },
        "object-assign": {
            "completed": true
        }
    }
}